tactik/__init__.py
tactik/clustering_pipeline.py
tactik/clustering_tuning.py
tactik/embeddings.py
tactik/preprocessing.py
tactik/topic_extraction.py
tactik/utilities.py
tactik/visualization.py
tactik-0.1.8.dist-info/licenses/license.txt
tactik-0.1.8.dist-info/METADATA
tactik-0.1.8.dist-info/WHEEL
tactik-0.1.8.dist-info/top_level.txt
tactik-0.1.8.dist-info/RECORD
