Metadata-Version: 2.4
Name: tactik
Version: 0.1.8
Summary: A Python library for topic modeling, clustering, and NLP analysis.
Author-email: Niklas Schulmeyer <nps0027@auburn.edu>
License: MIT
Project-URL: Homepage, https://github.com/npsAub/tactik
Project-URL: Issues, https://github.com/npsAub/tactik/issues
Requires-Python: >=3.9
License-File: license.txt
Requires-Dist: matplotlib>=3.8.0
Requires-Dist: numpy>=1.26.0
Requires-Dist: pandas>=2.0.0
Requires-Dist: scikit-learn>=1.3.0
Requires-Dist: scipy>=1.11.0
Requires-Dist: seaborn>=0.13.0
Requires-Dist: tqdm>=4.65.0
Requires-Dist: gensim>=4.3.0
Requires-Dist: hdbscan>=0.8.40
Requires-Dist: nltk>=3.8
Requires-Dist: sentence-transformers>=4.1.0
Requires-Dist: spacy>=3.8.0
Requires-Dist: torch>=2.3.0
Requires-Dist: transformers>=4.52.0
Requires-Dist: umap-learn>=0.5.7
Requires-Dist: yake>=0.4.8
Dynamic: license-file
